dtPyWebAppFramework/__init__.py
dtPyWebAppFramework/version.dat
dtPyWebAppFramework/_resources/base_template.html
dtPyWebAppFramework/_resources/card.html
dtPyWebAppFramework/_resources/disabled_card.html
dtPyWebAppFramework/_resources/error_card.html
dtPyWebAppFramework/_resources/exit.html
dtPyWebAppFramework/_resources/home.html
dtPyWebAppFramework/_resources/icon_library.html
dtPyWebAppFramework/_resources/please_wait.html
dtPyWebAppFramework/_resources/please_wait_template.html
dtPyWebAppFramework/_resources/tool_disabled.html
dtPyWebAppFramework/_resources/assets/bootstrap/css/bootstrap-grid.min.css
dtPyWebAppFramework/_resources/assets/bootstrap/css/bootstrap-reboot.min.css
dtPyWebAppFramework/_resources/assets/bootstrap/css/bootstrap.min.css
dtPyWebAppFramework/_resources/assets/bootstrap/js/bootstrap.bundle.min.js
dtPyWebAppFramework/_resources/assets/dropdown/css/style.css
dtPyWebAppFramework/_resources/assets/dropdown/js/navbar-dropdown.js
dtPyWebAppFramework/_resources/assets/images/Arch_AWS-Marketplace_Dark_64@5x.png
dtPyWebAppFramework/_resources/assets/images/Arch_AWS-Marketplace_Light_64@5x.png
dtPyWebAppFramework/_resources/assets/images/Arch_AWS-RoboMaker_64@5x.png
dtPyWebAppFramework/_resources/assets/images/check-tick-icon-14142.png
dtPyWebAppFramework/_resources/assets/images/complete.png
dtPyWebAppFramework/_resources/assets/images/loader.gif
dtPyWebAppFramework/_resources/assets/images/logo.png
dtPyWebAppFramework/_resources/assets/mobirise/css/mbr-additional.css
dtPyWebAppFramework/_resources/assets/smoothscroll/smooth-scroll.js
dtPyWebAppFramework/_resources/assets/socicon/css/styles.css
dtPyWebAppFramework/_resources/assets/socicon/fonts/socicon.eot
dtPyWebAppFramework/_resources/assets/socicon/fonts/socicon.svg
dtPyWebAppFramework/_resources/assets/socicon/fonts/socicon.ttf
dtPyWebAppFramework/_resources/assets/socicon/fonts/socicon.woff
dtPyWebAppFramework/_resources/assets/socicon/fonts/socicon.woff2
dtPyWebAppFramework-1.2.1.dist-info/LICENCE.txt
dtPyWebAppFramework-1.2.1.dist-info/METADATA
dtPyWebAppFramework-1.2.1.dist-info/WHEEL
dtPyWebAppFramework-1.2.1.dist-info/entry_points.txt
dtPyWebAppFramework-1.2.1.dist-info/top_level.txt
dtPyWebAppFramework-1.2.1.dist-info/RECORD
