Metadata-Version: 2.1
Name: dtPyWebAppFramework
Version: 1.2.1
Summary: A Python library to present a web based UI for Python Applications.
Author-email: Digital-Thought <dev@digital-thought.org>
Maintainer-email: Digital-Thought <dev@digital-thought.org>
License: MIT License
Project-URL: Homepage, https://github.com/Digital-Thought/dtPyWebAppFramework
Project-URL: Repository, https://github.com/Digital-Thought/dtPyWebAppFramework
Project-URL: Documentation, https://dtpywebappframework.readthedocs.io
Keywords: framework,logging,secrets,settings
Classifier: Development Status :: 5 - Production/Stable
Classifier: Intended Audience :: Developers
Classifier: Natural Language :: English
Classifier: Operating System :: Unix
Classifier: Operating System :: POSIX
Classifier: Operating System :: POSIX :: Linux
Classifier: Operating System :: MacOS
Classifier: Operating System :: Microsoft :: Windows
Classifier: Operating System :: OS Independent
Classifier: Programming Language :: Python :: 3.9
Classifier: Programming Language :: Python :: 3.10
Classifier: Programming Language :: Python :: 3.11
Classifier: License :: OSI Approved :: The Unlicense (Unlicense)
Classifier: Topic :: Security
Classifier: Topic :: Software Development :: Libraries :: Python Modules
Classifier: Topic :: System :: Systems Administration
Classifier: Topic :: Utilities
Requires-Python: >=3.9
License-File: LICENCE.txt
Requires-Dist: dtPyAppFramework==1.3.1
Requires-Dist: flask
